README.md
setup.py
simvcce/__init__.py
simvcce.egg-info/PKG-INFO
simvcce.egg-info/SOURCES.txt
simvcce.egg-info/dependency_links.txt
simvcce.egg-info/requires.txt
simvcce.egg-info/top_level.txt
simvcce/components/__init__.py
simvcce/components/compressor.py
simvcce/components/condenser.py
simvcce/components/device_siso.py
simvcce/components/evaporator.py
simvcce/components/expansionvalve.py
simvcce/components/flashchamber.py
simvcce/components/mixingchamber.py
simvcce/components/port.py
simvcce/vcc/__init__.py
simvcce/vcc/connector.py
simvcce/vcc/utils.py
simvcce/vcc/vccobj.py