Metadata-Version: 2.1
Name: simvcce
Version: 1.0.2
Summary: SimVCCE: The vapor-compression refrigeration cycle steady-state simulator for education
Home-page: https://github.com/thermalogic/SimVCCE
Author: Cheng Maohuaa
Author-email: cmh@seu.edu.cn
Platform: Windows64
Platform: Linux64
Classifier: Programming Language :: Python :: 3
Classifier: Programming Language :: C
Classifier: Topic :: Scientific/Engineering
Classifier: Topic :: Scientific/Engineering :: Chemistry
Classifier: Topic :: Scientific/Engineering :: Physics
Classifier: Topic :: Software Development :: Libraries :: Python Modules
